pyecospold/__init__.py
pyecospold/cas_validation.py
pyecospold/config.py
pyecospold/core.py
pyecospold/helpers.py
pyecospold/model_v1.py
pyecospold/model_v2.py
pyecospold/lxmlh/__init__.py
pyecospold/lxmlh/config.py
pyecospold/lxmlh/helpers.py
pyecospold/lxmlh/parsers.py
pyecospold/schemas/v1/EcoInventCategories.xsd
pyecospold/schemas/v1/EcoInventCompanyCodes.xsd
pyecospold/schemas/v1/EcoInventRegionalCodes.xsd
pyecospold/schemas/v1/EcoInventUnits.xsd
pyecospold/schemas/v1/EcoSpold01DataTypes.xsd
pyecospold/schemas/v1/EcoSpold01Dataset.xsd
pyecospold/schemas/v1/EcoSpold01ElementaryDataset.xsd
pyecospold/schemas/v1/EcoSpold01FlowData.xsd
pyecospold/schemas/v1/EcoSpold01ImpactDataset.xsd
pyecospold/schemas/v1/EcoSpold01MetaInformation.xsd
pyecospold/schemas/v1/XmlNamespace.xsd
pyecospold/schemas/v2/EcoSpold02.xsd
pyecospold/schemas/v2/EcoSpold02Activity.xsd
pyecospold/schemas/v2/EcoSpold02ChildActivity.xsd
pyecospold/schemas/v2/EcoSpold02ChildDataTypes.xsd
pyecospold/schemas/v2/EcoSpold02ChildFlowData.xsd
pyecospold/schemas/v2/EcoSpold02ChildMetaInformation.xsd
pyecospold/schemas/v2/EcoSpold02DataTypes.xsd
pyecospold/schemas/v2/EcoSpold02FlowData.xsd
pyecospold/schemas/v2/EcoSpold02MetaInformation.xsd
pyecospold/schemas/v2/XmlNamespace.xsd
pyecospold-4.0.1.dist-info/licenses/LICENSE
pyecospold-4.0.1.dist-info/METADATA
pyecospold-4.0.1.dist-info/WHEEL
pyecospold-4.0.1.dist-info/top_level.txt
pyecospold-4.0.1.dist-info/RECORD
