Metadata-Version: 2.4
Name: pyecospold
Version: 4.0.1
Summary: A Python package that converts ecospold XML formats to their Python equivalents and export the same data back to XML.
Author-email: Mina Sami <sami.mg@outlook.com>
Maintainer-email: Mina Sami <sami.mg@outlook.com>, Chris Mutel <cmutel@gmail.com>
Project-URL: source, https://github.com/brightway-lca/pyecospold
Project-URL: homepage, https://github.com/brightway-lca/pyecospold
Project-URL: tracker, https://github.com/brightway-lca/pyecospold/issues
Classifier: Development Status :: 4 - Beta
Classifier: Programming Language :: Python
Classifier: Programming Language :: Python :: 3
Classifier: Programming Language :: Python :: 3.8
Classifier: Programming Language :: Python :: 3.9
Classifier: Programming Language :: Python :: 3.10
Classifier: Programming Language :: Python :: 3.11
Classifier: Programming Language :: Python :: 3.12
Classifier: Natural Language :: English
Classifier: Operating System :: OS Independent
Requires-Python: >=3.8
License-File: LICENSE
Requires-Dist: lxml
Requires-Dist: numpy
Requires-Dist: python-dateutil
Provides-Extra: testing
Requires-Dist: pyecospold; extra == "testing"
Requires-Dist: pytest; extra == "testing"
Requires-Dist: pytest-cov; extra == "testing"
Requires-Dist: python-coveralls; extra == "testing"
Provides-Extra: dev
Requires-Dist: build; extra == "dev"
Requires-Dist: pre-commit; extra == "dev"
Requires-Dist: pylint; extra == "dev"
Requires-Dist: pytest; extra == "dev"
Requires-Dist: pytest-cov; extra == "dev"
Requires-Dist: pytest-randomly; extra == "dev"
Requires-Dist: setuptools; extra == "dev"
Requires-Dist: sphinx; extra == "dev"
Requires-Dist: sphinx-rtd-theme; extra == "dev"
Dynamic: license-file
